{"id":"u:e339c263ac5e","type":"page","body":[{"type":"form","id":"u:8f6dc62b29e2","title":"节点配置","body":[{"type":"input-text","label":"名称","name":"name","id":"u:fcc9a5524159","editorState":"default"},{"type":"radios","label":"事务范围","name":"tranScope","options":[{"label":"默认","value":"on"},{"label":"每个java节点","value":"everyJavaNode"},{"label":"每次交互","value":"everyRequest"},{"label":"关闭事务","value":"off"}],"id":"u:0d7bb8046669","value":"on","selectFirst":true}],"mode":"horizontal","onEvent":{"submitSucc":{"actions":[{"actionType":"broadcast","args":{"eventName":"formSubmited"},"data":"${event.data}"}]}}}],"asideResizor":false,"pullRefresh":{"disabled":true},"regions":["body"],"error":{"code":0},"status":0}